{
    "type": "collection",
    "entry": [
        {
            "fullUrl": "urn:uuid:d89a2eea-032c-4c84-8eb8-56ec6548c268",
            "resource": {
                "id": "d89a2eea-032c-4c84-8eb8-56ec6548c268",
                "text": {
                    "status": "generated",
                    "div": "<div>Generated by <a href=\"https://github.com/synthetichealth/synthea\">Synthea</a>. Version identifier: 1a8d765a5375bf72f3b7a92001940d05a6f21189</div>"
                },
                "extension": [
                    {
                        "url": "http://hl7.org/fhir/us/core/StructureDefinition/us-core-race",
                        "valueCodeableConcept": {
                            "coding": [
                                {
                                    "system": "http://hl7.org/fhir/v3/Race",
                                    "code": "2106-3",
                                    "display": "White"
                                }
                            ],
                            "text": "race"
                        }
                    },
                    {
                        "url": "http://hl7.org/fhir/us/core/StructureDefinition/us-core-ethnicity",
                        "valueCodeableConcept": {
                            "coding": [
                                {
                                    "system": "http://hl7.org/fhir/v3/Ethnicity",
                                    "code": "2186-5",
                                    "display": "Nonhispanic"
                                }
                            ],
                            "text": "ethnicity"
                        }
                    },
                    {
                        "url": "http://hl7.org/fhir/StructureDefinition/birthPlace",
                        "valueAddress": {
                            "city": "Barnstable Town",
                            "state": "MA",
                            "country": "US"
                        }
                    },
                    {
                        "url": "http://hl7.org/fhir/StructureDefinition/patient-mothersMaidenName",
                        "valueString": "Shawna Herman"
                    },
                    {
                        "url": "http://hl7.org/fhir/us/core/StructureDefinition/us-core-birthsex",
                        "valueCode": "M"
                    },
                    {
                        "url": "http://hl7.org/fhir/StructureDefinition/patient-interpreterRequired",
                        "valueBoolean": false
                    }
                ],
                "identifier": [
                    {
                        "system": "https://github.com/synthetichealth/synthea",
                        "value": "07ab3b7a-f1fc-4a2f-81bd-5265b86778eb"
                    },
                    {
                        "type": {
                            "coding": [
                                {
                                    "system": "http://hl7.org/fhir/identifier-type",
                                    "code": "SB"
                                }
                            ]
                        },
                        "system": "http://hl7.org/fhir/sid/us-ssn",
                        "value": "999963734"
                    },
                    {
                        "type": {
                            "coding": [
                                {
                                    "system": "http://hl7.org/fhir/v2/0203",
                                    "code": "DL"
                                }
                            ]
                        },
                        "system": "urn:oid:2.16.840.1.113883.4.3.25",
                        "value": "S99929203"
                    },
                    {
                        "type": {
                            "coding": [
                                {
                                    "system": "http://hl7.org/fhir/v2/0203",
                                    "code": "PPN"
                                }
                            ]
                        },
                        "value": "X81436681X"
                    },
                    {
                        "type": {
                            "coding": [
                                {
                                    "system": "http://hl7.org/fhir/v2/0203",
                                    "code": "MR"
                                }
                            ]
                        },
                        "system": "http://hospital.smarthealthit.org",
                        "value": "07ab3b7a-f1fc-4a2f-81bd-5265b86778eb"
                    }
                ],
                "name": [
                    {
                        "use": "official",
                        "family": [
                            "Corwin"
                        ],
                        "given": [
                            "Rickie"
                        ],
                        "prefix": [
                            "Mr."
                        ]
                    }
                ],
                "telecom": [
                    {
                        "system": "phone",
                        "value": "1-335-953-1028 x8264",
                        "use": "home"
                    }
                ],
                "gender": "male",
                "birthDate": "1990-03-30",
                "address": [
                    {
                        "extension": [
                            {
                                "extension": [
                                    {
                                        "url": "latitude",
                                        "valueDecimal": 42.50632414884104
                                    },
                                    {
                                        "url": "longitude",
                                        "valueDecimal": -72.52007885296429
                                    }
                                ],
                                "url": "http://hl7.org/fhir/StructureDefinition/geolocation"
                            }
                        ],
                        "line": [
                            "88698 Welch Mills",
                            "Suite 180"
                        ],
                        "city": "Leverett",
                        "state": "MA",
                        "postalCode": "01054",
                        "country": "US"
                    }
                ],
                "maritalStatus": {
                    "coding": [
                        {
                            "system": "http://hl7.org/fhir/v3/MaritalStatus",
                            "code": "M"
                        }
                    ],
                    "text": "M"
                },
                "multipleBirthBoolean": false,
                "communication": [
                    {
                        "language": {
                            "coding": [
                                {
                                    "system": "http://hl7.org/fhir/ValueSet/languages",
                                    "code": "en-US",
                                    "display": "English (United States)"
                                }
                            ]
                        }
                    }
                ],
                "resourceType": "Patient",
                "meta": {
                    "tag": [
                        {
                            "system": "https://smarthealthit.org/tags",
                            "code": "synthea-8-2017"
                        }
                    ]
                }
            }
        },
        {
            "fullUrl": "urn:uuid:792714e4-0929-4a02-ac88-ade396e9242d",
            "resource": {
                "id": "792714e4-0929-4a02-ac88-ade396e9242d",
                "type": {
                    "coding": [
                        {
                            "system": "http://hl7.org/fhir/ValueSet/organization-type",
                            "code": "prov",
                            "display": "Healthcare Provider"
                        }
                    ],
                    "text": "Healthcare Provider"
                },
                "name": "Synthetic Provider",
                "resourceType": "Organization",
                "meta": {
                    "tag": [
                        {
                            "system": "https://smarthealthit.org/tags",
                            "code": "synthea-8-2017"
                        }
                    ]
                }
            }
        },
        {
            "fullUrl": "urn:uuid:a4e17c97-de4f-40c2-a20e-abb17c5ee500",
            "resource": {
                "id": "a4e17c97-de4f-40c2-a20e-abb17c5ee500",
                "status": "finished",
                "class": "outpatient",
                "type": [
                    {
                        "coding": [
                            {
                                "system": "http://snomed.info/sct",
                                "code": "185349003"
                            }
                        ],
                        "text": "Outpatient Encounter"
                    }
                ],
                "patient": {
                    "reference": "urn:uuid:d89a2eea-032c-4c84-8eb8-56ec6548c268"
                },
                "period": {
                    "start": "2014-05-28T13:53:00+00:00",
                    "end": "2014-05-28T14:53:00+00:00"
                },
                "serviceProvider": {
                    "reference": "urn:uuid:792714e4-0929-4a02-ac88-ade396e9242d"
                },
                "resourceType": "Encounter",
                "meta": {
                    "tag": [
                        {
                            "system": "https://smarthealthit.org/tags",
                            "code": "synthea-8-2017"
                        }
                    ]
                }
            }
        },
        {
            "fullUrl": "urn:uuid:557818e0-b300-4480-a1ce-11e02b7dcb29",
            "resource": {
                "id": "557818e0-b300-4480-a1ce-11e02b7dcb29",
                "patient": {
                    "reference": "urn:uuid:d89a2eea-032c-4c84-8eb8-56ec6548c268"
                },
                "encounter": {
                    "reference": "urn:uuid:a4e17c97-de4f-40c2-a20e-abb17c5ee500"
                },
                "code": {
                    "coding": [
                        {
                            "system": "http://snomed.info/sct",
                            "code": "40055000",
                            "display": "Chronic sinusitis (disorder)"
                        }
                    ],
                    "text": "Chronic sinusitis (disorder)"
                },
                "clinicalStatus": "active",
                "verificationStatus": "confirmed",
                "onsetDateTime": "2008-06-06T15:45:42+00:00",
                "resourceType": "Condition",
                "meta": {
                    "tag": [
                        {
                            "system": "https://smarthealthit.org/tags",
                            "code": "synthea-8-2017"
                        }
                    ]
                }
            }
        },
        {
            "fullUrl": "urn:uuid:7830d6f3-fb50-471c-b57f-8e407d71d2fa",
            "resource": {
                "id": "7830d6f3-fb50-471c-b57f-8e407d71d2fa",
                "status": "final",
                "category": {
                    "coding": [
                        {
                            "system": "http://hl7.org/fhir/observation-category",
                            "code": "vital-signs"
                        }
                    ]
                },
                "code": {
                    "coding": [
                        {
                            "system": "http://loinc.org",
                            "code": "8302-2",
                            "display": "Body Height"
                        }
                    ],
                    "text": "Body Height"
                },
                "subject": {
                    "reference": "urn:uuid:d89a2eea-032c-4c84-8eb8-56ec6548c268"
                },
                "encounter": {
                    "reference": "urn:uuid:a4e17c97-de4f-40c2-a20e-abb17c5ee500"
                },
                "effectiveDateTime": "2014-05-28T13:53:00+00:00",
                "issued": "2014-05-28T13:53:00+00:00",
                "valueQuantity": {
                    "value": 172.66874326921246,
                    "unit": "cm",
                    "system": "http://unitsofmeasure.org/",
                    "code": "cm"
                },
                "resourceType": "Observation",
                "meta": {
                    "tag": [
                        {
                            "system": "https://smarthealthit.org/tags",
                            "code": "synthea-8-2017"
                        }
                    ]
                }
            }
        },
        {
            "fullUrl": "urn:uuid:6406cef3-c03a-4587-8991-78ddb0f0a023",
            "resource": {
                "id": "6406cef3-c03a-4587-8991-78ddb0f0a023",
                "status": "final",
                "category": {
                    "coding": [
                        {
                            "system": "http://hl7.org/fhir/observation-category",
                            "code": "vital-signs"
                        }
                    ]
                },
                "code": {
                    "coding": [
                        {
                            "system": "http://loinc.org",
                            "code": "29463-7",
                            "display": "Body Weight"
                        }
                    ],
                    "text": "Body Weight"
                },
                "subject": {
                    "reference": "urn:uuid:d89a2eea-032c-4c84-8eb8-56ec6548c268"
                },
                "encounter": {
                    "reference": "urn:uuid:a4e17c97-de4f-40c2-a20e-abb17c5ee500"
                },
                "effectiveDateTime": "2014-05-28T13:53:00+00:00",
                "issued": "2014-05-28T13:53:00+00:00",
                "valueQuantity": {
                    "value": 74.69502030860885,
                    "unit": "kg",
                    "system": "http://unitsofmeasure.org/",
                    "code": "kg"
                },
                "resourceType": "Observation",
                "meta": {
                    "tag": [
                        {
                            "system": "https://smarthealthit.org/tags",
                            "code": "synthea-8-2017"
                        }
                    ]
                }
            }
        },
        {
            "fullUrl": "urn:uuid:99a745db-af4b-44b7-9512-0321186e2235",
            "resource": {
                "id": "99a745db-af4b-44b7-9512-0321186e2235",
                "status": "final",
                "category": {
                    "coding": [
                        {
                            "system": "http://hl7.org/fhir/observation-category",
                            "code": "vital-signs"
                        }
                    ]
                },
                "code": {
                    "coding": [
                        {
                            "system": "http://loinc.org",
                            "code": "39156-5",
                            "display": "Body Mass Index"
                        }
                    ],
                    "text": "Body Mass Index"
                },
                "subject": {
                    "reference": "urn:uuid:d89a2eea-032c-4c84-8eb8-56ec6548c268"
                },
                "encounter": {
                    "reference": "urn:uuid:a4e17c97-de4f-40c2-a20e-abb17c5ee500"
                },
                "effectiveDateTime": "2014-05-28T13:53:00+00:00",
                "issued": "2014-05-28T13:53:00+00:00",
                "valueQuantity": {
                    "value": 25.053256999223652,
                    "unit": "kg/m2",
                    "system": "http://unitsofmeasure.org/",
                    "code": "kg/m2"
                },
                "resourceType": "Observation",
                "meta": {
                    "tag": [
                        {
                            "system": "https://smarthealthit.org/tags",
                            "code": "synthea-8-2017"
                        }
                    ]
                }
            }
        },
        {
            "fullUrl": "urn:uuid:053002fc-74ac-49a2-9b22-fe406fb1f38f",
            "resource": {
                "id": "053002fc-74ac-49a2-9b22-fe406fb1f38f",
                "status": "final",
                "category": {
                    "coding": [
                        {
                            "system": "http://hl7.org/fhir/observation-category",
                            "code": "vital-signs"
                        }
                    ]
                },
                "code": {
                    "coding": [
                        {
                            "system": "http://loinc.org",
                            "code": "55284-4",
                            "display": "Blood Pressure"
                        }
                    ]
                },
                "subject": {
                    "reference": "urn:uuid:d89a2eea-032c-4c84-8eb8-56ec6548c268"
                },
                "encounter": {
                    "reference": "urn:uuid:a4e17c97-de4f-40c2-a20e-abb17c5ee500"
                },
                "effectiveDateTime": "2014-05-28T13:53:00+00:00",
                "issued": "2014-05-28T13:53:00+00:00",
                "component": [
                    {
                        "code": {
                            "coding": [
                                {
                                    "system": "http://loinc.org",
                                    "code": "8480-6",
                                    "display": "Systolic Blood Pressure"
                                }
                            ],
                            "text": "Systolic Blood Pressure"
                        },
                        "valueQuantity": {
                            "value": 120,
                            "unit": "mmHg",
                            "system": "http://unitsofmeasure.org/",
                            "code": "mmHg"
                        }
                    },
                    {
                        "code": {
                            "coding": [
                                {
                                    "system": "http://loinc.org",
                                    "code": "8462-4",
                                    "display": "Diastolic Blood Pressure"
                                }
                            ],
                            "text": "Diastolic Blood Pressure"
                        },
                        "valueQuantity": {
                            "value": 76,
                            "unit": "mmHg",
                            "system": "http://unitsofmeasure.org/",
                            "code": "mmHg"
                        }
                    }
                ],
                "resourceType": "Observation",
                "meta": {
                    "tag": [
                        {
                            "system": "https://smarthealthit.org/tags",
                            "code": "synthea-8-2017"
                        }
                    ]
                }
            }
        },
        {
            "resource": {
                "status": "completed",
                "date": "2010-09-23T09:53:00-04:00",
                "vaccineCode": {
                    "coding": [
                        {
                            "system": "http://hl7.org/fhir/sid/cvx",
                            "code": "140",
                            "display": "Influenza, seasonal, injectable, preservative free"
                        }
                    ],
                    "text": "Influenza, seasonal, injectable, preservative free"
                },
                "patient": {
                    "reference": "urn:uuid:d89a2eea-032c-4c84-8eb8-56ec6548c268"
                },
                "wasNotGiven": false,
                "encounter": {
                    "reference": "urn:uuid:a4e17c97-de4f-40c2-a20e-abb17c5ee500"
                },
                "resourceType": "Immunization",
                "meta": {
                    "tag": [
                        {
                            "system": "https://smarthealthit.org/tags",
                            "code": "synthea-8-2017"
                        }
                    ]
                }
            }
        },
        {
            "resource": {
                "status": "completed",
                "date": "2010-09-23T09:53:00-04:00",
                "vaccineCode": {
                    "coding": [
                        {
                            "system": "http://hl7.org/fhir/sid/cvx",
                            "code": "113",
                            "display": "Td (adult) preservative free"
                        }
                    ],
                    "text": "Td (adult) preservative free"
                },
                "patient": {
                    "reference": "urn:uuid:d89a2eea-032c-4c84-8eb8-56ec6548c268"
                },
                "wasNotGiven": false,
                "encounter": {
                    "reference": "urn:uuid:a4e17c97-de4f-40c2-a20e-abb17c5ee500"
                },
                "resourceType": "Immunization",
                "meta": {
                    "tag": [
                        {
                            "system": "https://smarthealthit.org/tags",
                            "code": "synthea-8-2017"
                        }
                    ]
                }
            }
        },
        {
            "resource": {
                "dateWritten": "1997-12-21",
                "status": "active",
                "patient": {
                    "reference": "urn:uuid:d89a2eea-032c-4c84-8eb8-56ec6548c268"
                },
                "encounter": {
                    "reference": "urn:uuid:a4e17c97-de4f-40c2-a20e-abb17c5ee500"
                },
                "medicationCodeableConcept": {
                    "coding": [
                        {
                            "system": "http://www.nlm.nih.gov/research/umls/rxnorm",
                            "code": "834060",
                            "display": "Penicillin V Potassium 250 MG"
                        }
                    ],
                    "text": "Penicillin V Potassium 250 MG"
                },
                "resourceType": "MedicationOrder",
                "meta": {
                    "tag": [
                        {
                            "system": "https://smarthealthit.org/tags",
                            "code": "synthea-8-2017"
                        }
                    ]
                }
            }
        },
        {
            "fullUrl": "urn:uuid:dcc42f6a-f578-4c24-9114-659791b51f11",
            "resource": {
                "id": "dcc42f6a-f578-4c24-9114-659791b51f11",
                "status": "finished",
                "class": "outpatient",
                "type": [
                    {
                        "coding": [
                            {
                                "system": "http://snomed.info/sct",
                                "code": "185349003"
                            }
                        ],
                        "text": "Outpatient Encounter"
                    }
                ],
                "patient": {
                    "reference": "urn:uuid:d89a2eea-032c-4c84-8eb8-56ec6548c268"
                },
                "period": {
                    "start": "2017-09-18T18:47:39+00:00",
                    "end": "2017-09-18T19:47:39+00:00"
                },
                "serviceProvider": {
                    "reference": "urn:uuid:792714e4-0929-4a02-ac88-ade396e9242d"
                },
                "resourceType": "Encounter",
                "meta": {
                    "tag": [
                        {
                            "system": "https://smarthealthit.org/tags",
                            "code": "synthea-8-2017"
                        }
                    ]
                }
            }
        },
        {
            "fullUrl": "urn:uuid:27ec3b3c-7b63-4bf6-94c2-7e480e9c2ac8",
            "resource": {
                "id": "27ec3b3c-7b63-4bf6-94c2-7e480e9c2ac8",
                "status": "final",
                "category": {
                    "coding": [
                        {
                            "system": "http://hl7.org/fhir/observation-category",
                            "code": "vital-signs"
                        }
                    ]
                },
                "code": {
                    "coding": [
                        {
                            "system": "http://loinc.org",
                            "code": "8302-2",
                            "display": "Body Height"
                        }
                    ],
                    "text": "Body Height"
                },
                "subject": {
                    "reference": "urn:uuid:d89a2eea-032c-4c84-8eb8-56ec6548c268"
                },
                "encounter": {
                    "reference": "urn:uuid:dcc42f6a-f578-4c24-9114-659791b51f11"
                },
                "effectiveDateTime": "2017-09-18T18:47:39+00:00",
                "issued": "2017-09-18T18:47:39+00:00",
                "valueQuantity": {
                    "value": 172.66874326921246,
                    "unit": "cm",
                    "system": "http://unitsofmeasure.org/",
                    "code": "cm"
                },
                "resourceType": "Observation",
                "meta": {
                    "tag": [
                        {
                            "system": "https://smarthealthit.org/tags",
                            "code": "synthea-8-2017"
                        }
                    ]
                }
            }
        },
        {
            "fullUrl": "urn:uuid:82c0bb85-be34-451f-8c01-97cee62b127b",
            "resource": {
                "id": "82c0bb85-be34-451f-8c01-97cee62b127b",
                "status": "final",
                "category": {
                    "coding": [
                        {
                            "system": "http://hl7.org/fhir/observation-category",
                            "code": "vital-signs"
                        }
                    ]
                },
                "code": {
                    "coding": [
                        {
                            "system": "http://loinc.org",
                            "code": "29463-7",
                            "display": "Body Weight"
                        }
                    ],
                    "text": "Body Weight"
                },
                "subject": {
                    "reference": "urn:uuid:d89a2eea-032c-4c84-8eb8-56ec6548c268"
                },
                "encounter": {
                    "reference": "urn:uuid:dcc42f6a-f578-4c24-9114-659791b51f11"
                },
                "effectiveDateTime": "2017-09-18T18:47:39+00:00",
                "issued": "2017-09-18T18:47:39+00:00",
                "valueQuantity": {
                    "value": 79.43717111245549,
                    "unit": "kg",
                    "system": "http://unitsofmeasure.org/",
                    "code": "kg"
                },
                "resourceType": "Observation",
                "meta": {
                    "tag": [
                        {
                            "system": "https://smarthealthit.org/tags",
                            "code": "synthea-8-2017"
                        }
                    ]
                }
            }
        },
        {
            "fullUrl": "urn:uuid:bfd19f12-2372-4306-94a1-22f6c5379f83",
            "resource": {
                "id": "bfd19f12-2372-4306-94a1-22f6c5379f83",
                "status": "final",
                "category": {
                    "coding": [
                        {
                            "system": "http://hl7.org/fhir/observation-category",
                            "code": "vital-signs"
                        }
                    ]
                },
                "code": {
                    "coding": [
                        {
                            "system": "http://loinc.org",
                            "code": "39156-5",
                            "display": "Body Mass Index"
                        }
                    ],
                    "text": "Body Mass Index"
                },
                "subject": {
                    "reference": "urn:uuid:d89a2eea-032c-4c84-8eb8-56ec6548c268"
                },
                "encounter": {
                    "reference": "urn:uuid:dcc42f6a-f578-4c24-9114-659791b51f11"
                },
                "effectiveDateTime": "2017-09-18T18:47:39+00:00",
                "issued": "2017-09-18T18:47:39+00:00",
                "valueQuantity": {
                    "value": 26.64380911805281,
                    "unit": "kg/m2",
                    "system": "http://unitsofmeasure.org/",
                    "code": "kg/m2"
                },
                "resourceType": "Observation",
                "meta": {
                    "tag": [
                        {
                            "system": "https://smarthealthit.org/tags",
                            "code": "synthea-8-2017"
                        }
                    ]
                }
            }
        },
        {
            "fullUrl": "urn:uuid:aa8cd3f1-30c3-47ff-99a7-262ce1ac5b92",
            "resource": {
                "id": "aa8cd3f1-30c3-47ff-99a7-262ce1ac5b92",
                "status": "final",
                "category": {
                    "coding": [
                        {
                            "system": "http://hl7.org/fhir/observation-category",
                            "code": "vital-signs"
                        }
                    ]
                },
                "code": {
                    "coding": [
                        {
                            "system": "http://loinc.org",
                            "code": "55284-4",
                            "display": "Blood Pressure"
                        }
                    ]
                },
                "subject": {
                    "reference": "urn:uuid:d89a2eea-032c-4c84-8eb8-56ec6548c268"
                },
                "encounter": {
                    "reference": "urn:uuid:dcc42f6a-f578-4c24-9114-659791b51f11"
                },
                "effectiveDateTime": "2017-09-18T18:47:39+00:00",
                "issued": "2017-09-18T18:47:39+00:00",
                "component": [
                    {
                        "code": {
                            "coding": [
                                {
                                    "system": "http://loinc.org",
                                    "code": "8480-6",
                                    "display": "Systolic Blood Pressure"
                                }
                            ],
                            "text": "Systolic Blood Pressure"
                        },
                        "valueQuantity": {
                            "value": 127,
                            "unit": "mmHg",
                            "system": "http://unitsofmeasure.org/",
                            "code": "mmHg"
                        }
                    },
                    {
                        "code": {
                            "coding": [
                                {
                                    "system": "http://loinc.org",
                                    "code": "8462-4",
                                    "display": "Diastolic Blood Pressure"
                                }
                            ],
                            "text": "Diastolic Blood Pressure"
                        },
                        "valueQuantity": {
                            "value": 72,
                            "unit": "mmHg",
                            "system": "http://unitsofmeasure.org/",
                            "code": "mmHg"
                        }
                    }
                ],
                "resourceType": "Observation",
                "meta": {
                    "tag": [
                        {
                            "system": "https://smarthealthit.org/tags",
                            "code": "synthea-8-2017"
                        }
                    ]
                }
            }
        },
        {
            "resource": {
                "status": "completed",
                "date": "2014-01-14T13:47:39-05:00",
                "vaccineCode": {
                    "coding": [
                        {
                            "system": "http://hl7.org/fhir/sid/cvx",
                            "code": "140",
                            "display": "Influenza, seasonal, injectable, preservative free"
                        }
                    ],
                    "text": "Influenza, seasonal, injectable, preservative free"
                },
                "patient": {
                    "reference": "urn:uuid:d89a2eea-032c-4c84-8eb8-56ec6548c268"
                },
                "wasNotGiven": false,
                "encounter": {
                    "reference": "urn:uuid:dcc42f6a-f578-4c24-9114-659791b51f11"
                },
                "resourceType": "Immunization",
                "meta": {
                    "tag": [
                        {
                            "system": "https://smarthealthit.org/tags",
                            "code": "synthea-8-2017"
                        }
                    ]
                }
            }
        },
        {
            "fullUrl": "urn:uuid:3463d56f-8705-4d41-8636-2ddf151b5595",
            "resource": {
                "id": "3463d56f-8705-4d41-8636-2ddf151b5595",
                "status": "finished",
                "class": "ambulatory",
                "type": [
                    {
                        "coding": [
                            {
                                "system": "http://snomed.info/sct",
                                "code": "185345009"
                            }
                        ],
                        "text": "Encounter for symptom"
                    }
                ],
                "patient": {
                    "reference": "urn:uuid:d89a2eea-032c-4c84-8eb8-56ec6548c268"
                },
                "period": {
                    "start": "2018-08-03T12:29:54+00:00",
                    "end": "2019-12-30T09:19:09+00:00"
                },
                "reason": {
                    "coding": [
                        {
                            "system": "http://snomed.info/sct",
                            "code": "195662009",
                            "display": "Acute viral pharyngitis (disorder)"
                        }
                    ]
                },
                "serviceProvider": {
                    "reference": "urn:uuid:792714e4-0929-4a02-ac88-ade396e9242d"
                },
                "resourceType": "Encounter",
                "meta": {
                    "tag": [
                        {
                            "system": "https://smarthealthit.org/tags",
                            "code": "synthea-8-2017"
                        }
                    ]
                }
            }
        },
        {
            "fullUrl": "urn:uuid:b0d0a2f7-8071-4ec7-80a1-b7498f477acc",
            "resource": {
                "id": "b0d0a2f7-8071-4ec7-80a1-b7498f477acc",
                "patient": {
                    "reference": "urn:uuid:d89a2eea-032c-4c84-8eb8-56ec6548c268"
                },
                "encounter": {
                    "reference": "urn:uuid:3463d56f-8705-4d41-8636-2ddf151b5595"
                },
                "code": {
                    "coding": [
                        {
                            "system": "http://snomed.info/sct",
                            "code": "195662009",
                            "display": "Acute viral pharyngitis (disorder)"
                        }
                    ],
                    "text": "Acute viral pharyngitis (disorder)"
                },
                "clinicalStatus": "active",
                "verificationStatus": "confirmed",
                "onsetDateTime": "2018-07-30T12:57:51+00:00",
                "abatementDateTime": "2018-08-10T21:56:57+00:00",
                "resourceType": "Condition",
                "meta": {
                    "tag": [
                        {
                            "system": "https://smarthealthit.org/tags",
                            "code": "synthea-8-2017"
                        }
                    ]
                }
            }
        },
        {
            "fullUrl": "urn:uuid:e27344b3-dadd-4f25-a37d-da75f7e6da63",
            "resource": {
                "id": "e27344b3-dadd-4f25-a37d-da75f7e6da63",
                "patient": {
                    "reference": "urn:uuid:d89a2eea-032c-4c84-8eb8-56ec6548c268"
                },
                "encounter": {
                    "reference": "urn:uuid:3463d56f-8705-4d41-8636-2ddf151b5595"
                },
                "code": {
                    "coding": [
                        {
                            "system": "http://snomed.info/sct",
                            "code": "444814009",
                            "display": "Viral sinusitis (disorder)"
                        }
                    ],
                    "text": "Viral sinusitis (disorder)"
                },
                "clinicalStatus": "active",
                "verificationStatus": "confirmed",
                "onsetDateTime": "2019-12-23T15:45:42+00:00",
                "abatementDateTime": "2020-01-22T16:11:14+00:00",
                "resourceType": "Condition",
                "meta": {
                    "tag": [
                        {
                            "system": "https://smarthealthit.org/tags",
                            "code": "synthea-8-2017"
                        }
                    ]
                }
            }
        },
        {
            "fullUrl": "urn:uuid:48471922-376b-4c6a-9785-29583d420f54",
            "resource": {
                "id": "48471922-376b-4c6a-9785-29583d420f54",
                "status": "final",
                "category": {
                    "coding": [
                        {
                            "system": "http://hl7.org/fhir/observation-category",
                            "code": "vital-signs"
                        }
                    ]
                },
                "code": {
                    "coding": [
                        {
                            "system": "http://loinc.org",
                            "code": "8331-1",
                            "display": "Oral temperature"
                        }
                    ],
                    "text": "Oral temperature"
                },
                "subject": {
                    "reference": "urn:uuid:d89a2eea-032c-4c84-8eb8-56ec6548c268"
                },
                "encounter": {
                    "reference": "urn:uuid:3463d56f-8705-4d41-8636-2ddf151b5595"
                },
                "effectiveDateTime": "2018-08-03T12:29:54+00:00",
                "issued": "2018-08-03T12:29:54+00:00",
                "valueQuantity": {
                    "value": 38,
                    "unit": "Cel",
                    "system": "http://unitsofmeasure.org/",
                    "code": "Cel"
                },
                "resourceType": "Observation",
                "meta": {
                    "tag": [
                        {
                            "system": "https://smarthealthit.org/tags",
                            "code": "synthea-8-2017"
                        }
                    ]
                }
            }
        },
        {
            "fullUrl": "urn:uuid:4b7afeab-1de8-4071-8332-09ca8fbc2432",
            "resource": {
                "id": "4b7afeab-1de8-4071-8332-09ca8fbc2432",
                "status": "finished",
                "class": "ambulatory",
                "type": [
                    {
                        "coding": [
                            {
                                "system": "http://snomed.info/sct",
                                "code": "185345009"
                            }
                        ],
                        "text": "Encounter for symptom"
                    }
                ],
                "patient": {
                    "reference": "urn:uuid:d89a2eea-032c-4c84-8eb8-56ec6548c268"
                },
                "period": {
                    "start": "2019-12-30T09:19:09+00:00",
                    "end": "2019-12-30T09:19:09+00:00"
                },
                "reason": {
                    "coding": [
                        {
                            "system": "http://snomed.info/sct",
                            "code": "444814009",
                            "display": "Viral sinusitis (disorder)"
                        }
                    ]
                },
                "serviceProvider": {
                    "reference": "urn:uuid:792714e4-0929-4a02-ac88-ade396e9242d"
                },
                "resourceType": "Encounter",
                "meta": {
                    "tag": [
                        {
                            "system": "https://smarthealthit.org/tags",
                            "code": "synthea-8-2017"
                        }
                    ]
                }
            }
        },
        {
            "fullUrl": "urn:uuid:e6b1aa32-9c18-4841-83dc-ccce36cc2bf4",
            "resource": {
                "id": "e6b1aa32-9c18-4841-83dc-ccce36cc2bf4",
                "status": "finished",
                "class": "emergency",
                "type": [
                    {
                        "coding": [
                            {
                                "system": "http://snomed.info/sct",
                                "code": "50849002"
                            }
                        ],
                        "text": "Emergency room admission"
                    }
                ],
                "patient": {
                    "reference": "urn:uuid:d89a2eea-032c-4c84-8eb8-56ec6548c268"
                },
                "period": {
                    "start": "2020-06-26T11:08:33+00:00",
                    "end": "2020-06-26T11:08:33+00:00"
                },
                "serviceProvider": {
                    "reference": "urn:uuid:792714e4-0929-4a02-ac88-ade396e9242d"
                },
                "resourceType": "Encounter",
                "meta": {
                    "tag": [
                        {
                            "system": "https://smarthealthit.org/tags",
                            "code": "synthea-8-2017"
                        }
                    ]
                }
            }
        },
        {
            "fullUrl": "urn:uuid:eac26996-bb99-4181-ba51-179397f35830",
            "resource": {
                "id": "eac26996-bb99-4181-ba51-179397f35830",
                "patient": {
                    "reference": "urn:uuid:d89a2eea-032c-4c84-8eb8-56ec6548c268"
                },
                "encounter": {
                    "reference": "urn:uuid:e6b1aa32-9c18-4841-83dc-ccce36cc2bf4"
                },
                "code": {
                    "coding": [
                        {
                            "system": "http://snomed.info/sct",
                            "code": "44465007",
                            "display": "Sprain of ankle"
                        }
                    ],
                    "text": "Sprain of ankle"
                },
                "clinicalStatus": "active",
                "verificationStatus": "confirmed",
                "onsetDateTime": "2020-06-26T11:08:33+00:00",
                "abatementDateTime": "2020-07-27T20:05:47+00:00",
                "resourceType": "Condition",
                "meta": {
                    "tag": [
                        {
                            "system": "https://smarthealthit.org/tags",
                            "code": "synthea-8-2017"
                        }
                    ]
                }
            }
        },
        {
            "resource": {
                "subject": {
                    "reference": "urn:uuid:d89a2eea-032c-4c84-8eb8-56ec6548c268"
                },
                "status": "completed",
                "context": {
                    "reference": "urn:uuid:e6b1aa32-9c18-4841-83dc-ccce36cc2bf4"
                },
                "period": {
                    "start": "2020-06-26",
                    "end": "2020-07-27"
                },
                "category": [
                    {
                        "coding": [
                            {
                                "system": "http://snomed.info/sct",
                                "code": "91251008",
                                "display": "Physical therapy procedure"
                            }
                        ]
                    }
                ],
                "addresses": [
                    {
                        "reference": "urn:uuid:eac26996-bb99-4181-ba51-179397f35830"
                    }
                ],
                "activity": [
                    {
                        "detail": {
                            "code": {
                                "coding": [
                                    {
                                        "system": "http://snomed.info/sct",
                                        "code": "229586001",
                                        "display": "Rest, ice, compression and elevation treatment programme"
                                    }
                                ]
                            },
                            "status": "completed"
                        }
                    },
                    {
                        "detail": {
                            "code": {
                                "coding": [
                                    {
                                        "system": "http://snomed.info/sct",
                                        "code": "229070002",
                                        "display": "Stretching exercises"
                                    }
                                ]
                            },
                            "status": "completed"
                        }
                    }
                ],
                "resourceType": "CarePlan",
                "meta": {
                    "tag": [
                        {
                            "system": "https://smarthealthit.org/tags",
                            "code": "synthea-8-2017"
                        }
                    ]
                }
            }
        },
        {
            "resource": {
                "dateWritten": "2020-06-26",
                "status": "stopped",
                "patient": {
                    "reference": "urn:uuid:d89a2eea-032c-4c84-8eb8-56ec6548c268"
                },
                "encounter": {
                    "reference": "urn:uuid:e6b1aa32-9c18-4841-83dc-ccce36cc2bf4"
                },
                "medicationCodeableConcept": {
                    "coding": [
                        {
                            "system": "http://www.nlm.nih.gov/research/umls/rxnorm",
                            "code": "310965",
                            "display": "Ibuprofen 200 MG Oral Tablet"
                        }
                    ],
                    "text": "Ibuprofen 200 MG Oral Tablet"
                },
                "dosageInstruction": [
                    {
                        "asNeededBoolean": true
                    }
                ],
                "resourceType": "MedicationOrder",
                "meta": {
                    "tag": [
                        {
                            "system": "https://smarthealthit.org/tags",
                            "code": "synthea-8-2017"
                        }
                    ]
                }
            }
        },
        {
            "fullUrl": "urn:uuid:75cd2504-61c6-4007-84d2-6682737b021c",
            "resource": {
                "id": "75cd2504-61c6-4007-84d2-6682737b021c",
                "status": "finished",
                "class": "outpatient",
                "type": [
                    {
                        "coding": [
                            {
                                "system": "http://snomed.info/sct",
                                "code": "185349003"
                            }
                        ],
                        "text": "Outpatient Encounter"
                    }
                ],
                "patient": {
                    "reference": "urn:uuid:d89a2eea-032c-4c84-8eb8-56ec6548c268"
                },
                "period": {
                    "start": "2020-09-11T16:09:50+00:00",
                    "end": "2020-09-11T17:09:50+00:00"
                },
                "serviceProvider": {
                    "reference": "urn:uuid:792714e4-0929-4a02-ac88-ade396e9242d"
                },
                "resourceType": "Encounter",
                "meta": {
                    "tag": [
                        {
                            "system": "https://smarthealthit.org/tags",
                            "code": "synthea-8-2017"
                        }
                    ]
                }
            }
        },
        {
            "fullUrl": "urn:uuid:670c2e8c-b206-4137-80a2-d10e87cd2ff1",
            "resource": {
                "id": "670c2e8c-b206-4137-80a2-d10e87cd2ff1",
                "status": "final",
                "category": {
                    "coding": [
                        {
                            "system": "http://hl7.org/fhir/observation-category",
                            "code": "vital-signs"
                        }
                    ]
                },
                "code": {
                    "coding": [
                        {
                            "system": "http://loinc.org",
                            "code": "8302-2",
                            "display": "Body Height"
                        }
                    ],
                    "text": "Body Height"
                },
                "subject": {
                    "reference": "urn:uuid:d89a2eea-032c-4c84-8eb8-56ec6548c268"
                },
                "encounter": {
                    "reference": "urn:uuid:75cd2504-61c6-4007-84d2-6682737b021c"
                },
                "effectiveDateTime": "2020-09-11T16:09:50+00:00",
                "issued": "2020-09-11T16:09:50+00:00",
                "valueQuantity": {
                    "value": 172.66874326921246,
                    "unit": "cm",
                    "system": "http://unitsofmeasure.org/",
                    "code": "cm"
                },
                "resourceType": "Observation",
                "meta": {
                    "tag": [
                        {
                            "system": "https://smarthealthit.org/tags",
                            "code": "synthea-8-2017"
                        }
                    ]
                }
            }
        },
        {
            "fullUrl": "urn:uuid:1353b233-0fb8-42a2-bd78-b484ad221890",
            "resource": {
                "id": "1353b233-0fb8-42a2-bd78-b484ad221890",
                "status": "final",
                "category": {
                    "coding": [
                        {
                            "system": "http://hl7.org/fhir/observation-category",
                            "code": "vital-signs"
                        }
                    ]
                },
                "code": {
                    "coding": [
                        {
                            "system": "http://loinc.org",
                            "code": "29463-7",
                            "display": "Body Weight"
                        }
                    ],
                    "text": "Body Weight"
                },
                "subject": {
                    "reference": "urn:uuid:d89a2eea-032c-4c84-8eb8-56ec6548c268"
                },
                "encounter": {
                    "reference": "urn:uuid:75cd2504-61c6-4007-84d2-6682737b021c"
                },
                "effectiveDateTime": "2020-09-11T16:09:50+00:00",
                "issued": "2020-09-11T16:09:50+00:00",
                "valueQuantity": {
                    "value": 84.10727093474006,
                    "unit": "kg",
                    "system": "http://unitsofmeasure.org/",
                    "code": "kg"
                },
                "resourceType": "Observation",
                "meta": {
                    "tag": [
                        {
                            "system": "https://smarthealthit.org/tags",
                            "code": "synthea-8-2017"
                        }
                    ]
                }
            }
        },
        {
            "fullUrl": "urn:uuid:d081d233-ca28-4566-89d0-c1af66186c15",
            "resource": {
                "id": "d081d233-ca28-4566-89d0-c1af66186c15",
                "status": "final",
                "category": {
                    "coding": [
                        {
                            "system": "http://hl7.org/fhir/observation-category",
                            "code": "vital-signs"
                        }
                    ]
                },
                "code": {
                    "coding": [
                        {
                            "system": "http://loinc.org",
                            "code": "39156-5",
                            "display": "Body Mass Index"
                        }
                    ],
                    "text": "Body Mass Index"
                },
                "subject": {
                    "reference": "urn:uuid:d89a2eea-032c-4c84-8eb8-56ec6548c268"
                },
                "encounter": {
                    "reference": "urn:uuid:75cd2504-61c6-4007-84d2-6682737b021c"
                },
                "effectiveDateTime": "2020-09-11T16:09:50+00:00",
                "issued": "2020-09-11T16:09:50+00:00",
                "valueQuantity": {
                    "value": 28.21019480984757,
                    "unit": "kg/m2",
                    "system": "http://unitsofmeasure.org/",
                    "code": "kg/m2"
                },
                "resourceType": "Observation",
                "meta": {
                    "tag": [
                        {
                            "system": "https://smarthealthit.org/tags",
                            "code": "synthea-8-2017"
                        }
                    ]
                }
            }
        },
        {
            "fullUrl": "urn:uuid:479374bf-b165-4605-aba2-c859861356a9",
            "resource": {
                "id": "479374bf-b165-4605-aba2-c859861356a9",
                "status": "final",
                "category": {
                    "coding": [
                        {
                            "system": "http://hl7.org/fhir/observation-category",
                            "code": "vital-signs"
                        }
                    ]
                },
                "code": {
                    "coding": [
                        {
                            "system": "http://loinc.org",
                            "code": "55284-4",
                            "display": "Blood Pressure"
                        }
                    ]
                },
                "subject": {
                    "reference": "urn:uuid:d89a2eea-032c-4c84-8eb8-56ec6548c268"
                },
                "encounter": {
                    "reference": "urn:uuid:75cd2504-61c6-4007-84d2-6682737b021c"
                },
                "effectiveDateTime": "2020-09-11T16:09:50+00:00",
                "issued": "2020-09-11T16:09:50+00:00",
                "component": [
                    {
                        "code": {
                            "coding": [
                                {
                                    "system": "http://loinc.org",
                                    "code": "8480-6",
                                    "display": "Systolic Blood Pressure"
                                }
                            ],
                            "text": "Systolic Blood Pressure"
                        },
                        "valueQuantity": {
                            "value": 101,
                            "unit": "mmHg",
                            "system": "http://unitsofmeasure.org/",
                            "code": "mmHg"
                        }
                    },
                    {
                        "code": {
                            "coding": [
                                {
                                    "system": "http://loinc.org",
                                    "code": "8462-4",
                                    "display": "Diastolic Blood Pressure"
                                }
                            ],
                            "text": "Diastolic Blood Pressure"
                        },
                        "valueQuantity": {
                            "value": 71,
                            "unit": "mmHg",
                            "system": "http://unitsofmeasure.org/",
                            "code": "mmHg"
                        }
                    }
                ],
                "resourceType": "Observation",
                "meta": {
                    "tag": [
                        {
                            "system": "https://smarthealthit.org/tags",
                            "code": "synthea-8-2017"
                        }
                    ]
                }
            }
        },
        {
            "fullUrl": "urn:uuid:526deec1-1b90-49e4-af6d-9e18e86381a4",
            "resource": {
                "id": "526deec1-1b90-49e4-af6d-9e18e86381a4",
                "status": "final",
                "category": {
                    "coding": [
                        {
                            "system": "http://hl7.org/fhir/observation-category",
                            "code": "laboratory"
                        }
                    ]
                },
                "code": {
                    "coding": [
                        {
                            "system": "http://loinc.org",
                            "code": "2093-3",
                            "display": "Total Cholesterol"
                        }
                    ],
                    "text": "Total Cholesterol"
                },
                "subject": {
                    "reference": "urn:uuid:d89a2eea-032c-4c84-8eb8-56ec6548c268"
                },
                "encounter": {
                    "reference": "urn:uuid:75cd2504-61c6-4007-84d2-6682737b021c"
                },
                "effectiveDateTime": "2020-09-11T16:09:50+00:00",
                "issued": "2020-09-11T16:09:50+00:00",
                "valueQuantity": {
                    "value": 175,
                    "unit": "mg/dL",
                    "system": "http://unitsofmeasure.org/",
                    "code": "mg/dL"
                },
                "resourceType": "Observation",
                "meta": {
                    "tag": [
                        {
                            "system": "https://smarthealthit.org/tags",
                            "code": "synthea-8-2017"
                        }
                    ]
                }
            }
        },
        {
            "fullUrl": "urn:uuid:5eabd3c4-6bd3-483a-bc2f-9c0153eb6c64",
            "resource": {
                "id": "5eabd3c4-6bd3-483a-bc2f-9c0153eb6c64",
                "status": "final",
                "category": {
                    "coding": [
                        {
                            "system": "http://hl7.org/fhir/observation-category",
                            "code": "laboratory"
                        }
                    ]
                },
                "code": {
                    "coding": [
                        {
                            "system": "http://loinc.org",
                            "code": "2571-8",
                            "display": "Triglycerides"
                        }
                    ],
                    "text": "Triglycerides"
                },
                "subject": {
                    "reference": "urn:uuid:d89a2eea-032c-4c84-8eb8-56ec6548c268"
                },
                "encounter": {
                    "reference": "urn:uuid:75cd2504-61c6-4007-84d2-6682737b021c"
                },
                "effectiveDateTime": "2020-09-11T16:09:50+00:00",
                "issued": "2020-09-11T16:09:50+00:00",
                "valueQuantity": {
                    "value": 119,
                    "unit": "mg/dL",
                    "system": "http://unitsofmeasure.org/",
                    "code": "mg/dL"
                },
                "resourceType": "Observation",
                "meta": {
                    "tag": [
                        {
                            "system": "https://smarthealthit.org/tags",
                            "code": "synthea-8-2017"
                        }
                    ]
                }
            }
        },
        {
            "fullUrl": "urn:uuid:d4c3de97-de80-43d9-91a8-80ee4cdff8bc",
            "resource": {
                "id": "d4c3de97-de80-43d9-91a8-80ee4cdff8bc",
                "status": "final",
                "category": {
                    "coding": [
                        {
                            "system": "http://hl7.org/fhir/observation-category",
                            "code": "laboratory"
                        }
                    ]
                },
                "code": {
                    "coding": [
                        {
                            "system": "http://loinc.org",
                            "code": "18262-6",
                            "display": "Low Density Lipoprotein Cholesterol"
                        }
                    ],
                    "text": "Low Density Lipoprotein Cholesterol"
                },
                "subject": {
                    "reference": "urn:uuid:d89a2eea-032c-4c84-8eb8-56ec6548c268"
                },
                "encounter": {
                    "reference": "urn:uuid:75cd2504-61c6-4007-84d2-6682737b021c"
                },
                "effectiveDateTime": "2020-09-11T16:09:50+00:00",
                "issued": "2020-09-11T16:09:50+00:00",
                "valueQuantity": {
                    "value": 73,
                    "unit": "mg/dL",
                    "system": "http://unitsofmeasure.org/",
                    "code": "mg/dL"
                },
                "resourceType": "Observation",
                "meta": {
                    "tag": [
                        {
                            "system": "https://smarthealthit.org/tags",
                            "code": "synthea-8-2017"
                        }
                    ]
                }
            }
        },
        {
            "fullUrl": "urn:uuid:f0fd0199-1aaa-4b23-85ad-118bfaa86b5e",
            "resource": {
                "id": "f0fd0199-1aaa-4b23-85ad-118bfaa86b5e",
                "status": "final",
                "category": {
                    "coding": [
                        {
                            "system": "http://hl7.org/fhir/observation-category",
                            "code": "laboratory"
                        }
                    ]
                },
                "code": {
                    "coding": [
                        {
                            "system": "http://loinc.org",
                            "code": "2085-9",
                            "display": "High Density Lipoprotein Cholesterol"
                        }
                    ],
                    "text": "High Density Lipoprotein Cholesterol"
                },
                "subject": {
                    "reference": "urn:uuid:d89a2eea-032c-4c84-8eb8-56ec6548c268"
                },
                "encounter": {
                    "reference": "urn:uuid:75cd2504-61c6-4007-84d2-6682737b021c"
                },
                "effectiveDateTime": "2020-09-11T16:09:50+00:00",
                "issued": "2020-09-11T16:09:50+00:00",
                "valueQuantity": {
                    "value": 78,
                    "unit": "mg/dL",
                    "system": "http://unitsofmeasure.org/",
                    "code": "mg/dL"
                },
                "resourceType": "Observation",
                "meta": {
                    "tag": [
                        {
                            "system": "https://smarthealthit.org/tags",
                            "code": "synthea-8-2017"
                        }
                    ]
                }
            }
        },
        {
            "fullUrl": "urn:uuid:123ff001-4cf0-4853-868b-632e61449980",
            "resource": {
                "id": "123ff001-4cf0-4853-868b-632e61449980",
                "status": "final",
                "code": {
                    "coding": [
                        {
                            "system": "http://loinc.org",
                            "code": "57698-3",
                            "display": "Lipid Panel"
                        }
                    ]
                },
                "subject": {
                    "reference": "urn:uuid:d89a2eea-032c-4c84-8eb8-56ec6548c268"
                },
                "encounter": {
                    "reference": "urn:uuid:75cd2504-61c6-4007-84d2-6682737b021c"
                },
                "effectiveDateTime": "2020-09-11T16:09:50+00:00",
                "issued": "2020-09-11T16:09:50+00:00",
                "result": [
                    {
                        "reference": "urn:uuid:526deec1-1b90-49e4-af6d-9e18e86381a4",
                        "display": "Total Cholesterol"
                    },
                    {
                        "reference": "urn:uuid:5eabd3c4-6bd3-483a-bc2f-9c0153eb6c64",
                        "display": "Triglycerides"
                    },
                    {
                        "reference": "urn:uuid:d4c3de97-de80-43d9-91a8-80ee4cdff8bc",
                        "display": "Low Density Lipoprotein Cholesterol"
                    },
                    {
                        "reference": "urn:uuid:f0fd0199-1aaa-4b23-85ad-118bfaa86b5e",
                        "display": "High Density Lipoprotein Cholesterol"
                    }
                ],
                "resourceType": "DiagnosticReport",
                "meta": {
                    "tag": [
                        {
                            "system": "https://smarthealthit.org/tags",
                            "code": "synthea-8-2017"
                        }
                    ]
                }
            }
        },
        {
            "resource": {
                "subject": {
                    "reference": "urn:uuid:d89a2eea-032c-4c84-8eb8-56ec6548c268"
                },
                "status": "completed",
                "code": {
                    "coding": [
                        {
                            "system": "http://snomed.info/sct",
                            "code": "428191000124101",
                            "display": "Documentation of current medications"
                        }
                    ],
                    "text": "Documentation of current medications"
                },
                "performedDateTime": "2020-09-11T16:09:50+00:00",
                "encounter": {
                    "reference": "urn:uuid:75cd2504-61c6-4007-84d2-6682737b021c"
                },
                "resourceType": "Procedure",
                "meta": {
                    "tag": [
                        {
                            "system": "https://smarthealthit.org/tags",
                            "code": "synthea-8-2017"
                        }
                    ]
                }
            }
        },
        {
            "resource": {
                "status": "completed",
                "date": "2017-01-07T11:09:50-05:00",
                "vaccineCode": {
                    "coding": [
                        {
                            "system": "http://hl7.org/fhir/sid/cvx",
                            "code": "140",
                            "display": "Influenza, seasonal, injectable, preservative free"
                        }
                    ],
                    "text": "Influenza, seasonal, injectable, preservative free"
                },
                "patient": {
                    "reference": "urn:uuid:d89a2eea-032c-4c84-8eb8-56ec6548c268"
                },
                "wasNotGiven": false,
                "encounter": {
                    "reference": "urn:uuid:75cd2504-61c6-4007-84d2-6682737b021c"
                },
                "resourceType": "Immunization",
                "meta": {
                    "tag": [
                        {
                            "system": "https://smarthealthit.org/tags",
                            "code": "synthea-8-2017"
                        }
                    ]
                }
            }
        }
    ],
    "resourceType": "Bundle"
}